mediagui/__init__.py
mediagui/gui.py
mediagui/list_widget.py
mediagui/openh264-1.8.0-win64.dll
mediagui/worker.py
mediagui-1.0.3.dist-info/licenses/LICENSE.txt
mediagui-1.0.3.dist-info/METADATA
mediagui-1.0.3.dist-info/WHEEL
mediagui-1.0.3.dist-info/entry_points.txt
mediagui-1.0.3.dist-info/top_level.txt
mediagui-1.0.3.dist-info/RECORD
