Metadata-Version: 2.4
Name: mediagui
Version: 1.0.3
Summary: A Python package with a GUI for video formatting
Home-page: https://github.com/khicken/mediaGUI
Author: Kaleb Kim
Author-email: mail@kalebkim.com
Classifier: Programming Language :: Python :: 3
Classifier: License :: OSI Approved :: MIT License
Classifier: Operating System :: OS Independent
Requires-Python: >=3.9
License-File: LICENSE.txt
Requires-Dist: numpy>=1.26.0
Requires-Dist: opencv-python<5,>=4.8.1
Requires-Dist: PyQt6<7,>=6.6.0
Requires-Dist: PyQt6-Qt6<7,>=6.6.0
Requires-Dist: PyQt6-sip<14,>=13.5.0
Dynamic: author
Dynamic: author-email
Dynamic: classifier
Dynamic: description
Dynamic: description-content-type
Dynamic: home-page
Dynamic: license-file
Dynamic: requires-dist
Dynamic: requires-python
Dynamic: summary
